asana_typed/__init__.py
asana_typed/_version.py
asana_typed/asana.py
asana_typed/query.py
asana_typed-0.1.2a1.dist-info/LICENSE
asana_typed-0.1.2a1.dist-info/METADATA
asana_typed-0.1.2a1.dist-info/WHEEL
asana_typed-0.1.2a1.dist-info/top_level.txt
asana_typed-0.1.2a1.dist-info/zip-safe
asana_typed-0.1.2a1.dist-info/RECORD
