Metadata-Version: 2.1
Name: asana-typed
Version: 0.1.2a1
Summary: Asana typed API Objects
Home-page: https://github.com/will7200/asana-typed
Author: will7200
Author-email: yugiohbotgit@gmail.com
License: MIT
Keywords: asana api typed python-asana
Platform: win32
Classifier: Development Status :: 3 - Alpha
Classifier: Operating System :: Microsoft :: Windows
Classifier: Operating System :: MacOS
Classifier: Intended Audience :: End Users/Desktop
Classifier: Programming Language :: Python
Classifier: Programming Language :: Python :: 3
Classifier: Programming Language :: Python :: 3.6
Classifier: License :: OSI Approved :: MIT License
Requires-Python: >=3.6
